CHANGELOG.md
COPYING.txt
MANIFEST.in
README.rst
setup.cfg
setup.py
tailbone_corepos/__init__.py
tailbone_corepos/_version.py
tailbone_corepos/db.py
tailbone_corepos/menus.py
tailbone_corepos/provider.py
tailbone_corepos.egg-info/PKG-INFO
tailbone_corepos.egg-info/SOURCES.txt
tailbone_corepos.egg-info/dependency_links.txt
tailbone_corepos.egg-info/entry_points.txt
tailbone_corepos.egg-info/not-zip-safe
tailbone_corepos.egg-info/requires.txt
tailbone_corepos.egg-info/top_level.txt
tailbone_corepos/templates/corepos-util.mako
tailbone_corepos/templates/batch/corepos-member/view_row.mako
tailbone_corepos/templates/core-pos/origins/index.mako
tailbone_corepos/templates/core-pos/origins/countries/index.mako
tailbone_corepos/templates/core-pos/origins/regions/index.mako
tailbone_corepos/templates/core-pos/origins/stateprov/index.mako
tailbone_corepos/templates/core-pos/products/index.mako
tailbone_corepos/templates/core-pos/products/view.mako
tailbone_corepos/templates/core-pos/products-user/index.mako
tailbone_corepos/templates/core-pos/user-groups/view.mako
tailbone_corepos/templates/core-pos/vendor-items/index.mako
tailbone_corepos/templates/core-pos/vendors/index.mako
tailbone_corepos/templates/corepos/transaction-details/current/index.mako
tailbone_corepos/templates/purchases/view.mako
tailbone_corepos/views/__init__.py
tailbone_corepos/views/customers.py
tailbone_corepos/views/departments.py
tailbone_corepos/views/employees.py
tailbone_corepos/views/members.py
tailbone_corepos/views/people.py
tailbone_corepos/views/products.py
tailbone_corepos/views/purchases.py
tailbone_corepos/views/stores.py
tailbone_corepos/views/subdepartments.py
tailbone_corepos/views/taxes.py
tailbone_corepos/views/tenders.py
tailbone_corepos/views/vendors.py
tailbone_corepos/views/batch/__init__.py
tailbone_corepos/views/batch/coremember.py
tailbone_corepos/views/batch/equityimport.py
tailbone_corepos/views/batch/vendorcatalog.py
tailbone_corepos/views/corepos/__init__.py
tailbone_corepos/views/corepos/batches.py
tailbone_corepos/views/corepos/coupons.py
tailbone_corepos/views/corepos/customers.py
tailbone_corepos/views/corepos/departments.py
tailbone_corepos/views/corepos/employees.py
tailbone_corepos/views/corepos/groups.py
tailbone_corepos/views/corepos/lanes.py
